wd/__init__.py
wd/pareto.py
wd/query_view.py
wd/truly_tabular_display.py
wd/version.py
wd/wdgrid_cmd.py
wd/wditem_search.py
wd/webserver.py
wdgrid-0.2.0.dist-info/METADATA
wdgrid-0.2.0.dist-info/WHEEL
wdgrid-0.2.0.dist-info/entry_points.txt
wdgrid-0.2.0.dist-info/licenses/LICENSE
wdgrid-0.2.0.dist-info/RECORD
