Metadata-Version: 2.4
Name: wdgrid
Version: 0.2.0
Summary: wikidata grid display and sync
Project-URL: Home, https://github.com/WolfgangFahl/wdgrid
Project-URL: Documentation, https://wiki.bitplan.com/index.php/Wdgrid
Project-URL: Source, https://github.com/WolfgangFahl/wdgrid
Author-email: Wolfgang Fahl <wf@bitplan.com>
Maintainer-email: Wolfgang Fahl <wf@bitplan.com>
License-Expression: Apache-2.0
License-File: LICENSE
Keywords: nicegui,sync,ui,wikidata
Classifier: Development Status :: 4 - Beta
Classifier: Environment :: Console
Classifier: Intended Audience :: Developers
Classifier: Intended Audience :: Education
Classifier: License :: OSI Approved :: Apache Software License
Classifier: Operating System :: OS Independent
Classifier: Programming Language :: Python :: 3 :: Only
Classifier: Programming Language :: Python :: 3.10
Classifier: Programming Language :: Python :: 3.11
Classifier: Programming Language :: Python :: 3.12
Classifier: Programming Language :: Python :: 3.13
Classifier: Topic :: Software Development :: Libraries :: Python Modules
Requires-Python: >=3.10
Requires-Dist: ngwidgets>=0.27.1
Requires-Dist: py-ez-wikidata>=0.3.1
Requires-Dist: pylodstorage>=0.16.4
Requires-Dist: tabulate>=0.9.0
Provides-Extra: test
Requires-Dist: green; extra == 'test'
